{
    "arch": "x86_64",
    "build": "py312h06a4308_0",
    "build_number": 0,
    "build_string": "py312h06a4308_0",
    "channel": "https://repo.anaconda.com/pkgs/main/linux-64",
    "constrains": [],
    "depends": [
        "comm >=0.1.1",
        "debugpy >=1.6.5",
        "ipython >=7.23.1",
        "jupyter_client >=6.1.12",
        "jupyter_core >=4.12,!=5.0.*",
        "matplotlib-inline >=0.1",
        "nest-asyncio",
        "packaging",
        "psutil",
        "python >=3.12,<3.13.0a0",
        "pyzmq >=24",
        "tornado >=6.1",
        "traitlets >=5.4.0"
    ],
    "fn": "ipykernel-6.28.0-py312h06a4308_0.conda",
    "license": "BSD-3-Clause",
    "license_family": "BSD",
    "md5": "b488eb4fadcff89d5a2cf097a5c7a91b",
    "name": "ipykernel",
    "platform": "linux",
    "sha256": "1c96517aa1d799463acc100f8c46d447c66de53d7c3e14ce9ab5b177813a902c",
    "size": 246293,
    "subdir": "linux-64",
    "timestamp": 1705934373987,
    "track_features": "",
    "url": "https://repo.anaconda.com/pkgs/main/linux-64/ipykernel-6.28.0-py312h06a4308_0.conda",
    "version": "6.28.0"
}